petwee.py
petwee-0.1.0.dist-info/LICENSE
petwee-0.1.0.dist-info/METADATA
petwee-0.1.0.dist-info/WHEEL
petwee-0.1.0.dist-info/top_level.txt
petwee-0.1.0.dist-info/RECORD
