Metadata-Version: 2.1
Name: petwee
Version: 0.1.0
Summary: an ORM/ODM for Google Datastore/MongoDB, featuring a compatible interface with Peewee.
Author-email: cdhigh <chsqyuan@gmail.com>
License: MIT License
Project-URL: Homepage, https://github.com/cdhigh/petwee
Keywords: petwee,peewee,ORM,ODM,google cloud datastore,MongoDB
Classifier: License :: OSI Approved :: MIT License
Classifier: Intended Audience :: Developers
Classifier: Operating System :: OS Independent
Classifier: Natural Language :: English
Classifier: Programming Language :: Python
Classifier: Programming Language :: Python :: 3
Classifier: Programming Language :: Python :: 3.8
Classifier: Programming Language :: Python :: 3.9
Classifier: Programming Language :: Python :: 3.10
Classifier: Programming Language :: Python :: 3.11
Classifier: Programming Language :: Python :: 3.12
Classifier: Topic :: Software Development :: Libraries
Requires-Python: >=3.6
License-File: LICENSE
Requires-Dist: google-cloud-datastore
Requires-Dist: pymongo
